srt.py
srt2-3.5.4.data/scripts/srt
srt2-3.5.4.data/scripts/srt-deduplicate
srt2-3.5.4.data/scripts/srt-fixed-timeshift
srt2-3.5.4.data/scripts/srt-linear-timeshift
srt2-3.5.4.data/scripts/srt-lines-matching
srt2-3.5.4.data/scripts/srt-mux
srt2-3.5.4.data/scripts/srt-normalise
srt2-3.5.4.data/scripts/srt-play
srt2-3.5.4.data/scripts/srt-process
srt2-3.5.4.dist-info/licenses/LICENSE
srt_tools/__init__.py
srt_tools/utils.py
srt2-3.5.4.dist-info/METADATA
srt2-3.5.4.dist-info/WHEEL
srt2-3.5.4.dist-info/top_level.txt
srt2-3.5.4.dist-info/RECORD
